fastapi_microservice_helper/__init__.py
fastapi_microservice_helper/base_microservice_client.py
fastapi_microservice_helper/clone_generation.py
fastapi_microservice_helper/code_generation.py
fastapi_microservice_helper/config.py
fastapi_microservice_helper/decorator.py
fastapi_microservice_helper/helper.py
fastapi_microservice_helper/sdk_builder.py
fastapi_microservice_helper/sdk_template.py
fastapi_microservice_helper/models/generation_detail.py
fastapi_microservice_helper/models/method_detail.py
fastapi_microservice_helper-0.0.42.dist-info/METADATA
fastapi_microservice_helper-0.0.42.dist-info/WHEEL
fastapi_microservice_helper-0.0.42.dist-info/licenses/LICENSE
fastapi_microservice_helper-0.0.42.dist-info/RECORD
