Metadata-Version: 2.4
Name: fastapi_microservice_helper
Version: 0.0.42
Summary: FastAPI Microservice Helper
Project-URL: Homepage, https://github.com/megatron-global/fastapi-microservice-helper
Project-URL: Bug Tracker, https://github.com/megatron-global/fastapi-microservice-helper/issues
Author-email: Dzung Nguyen <dung@megatron-solutions.com>
License-File: LICENSE
Classifier: License :: OSI Approved :: MIT License
Classifier: Operating System :: OS Independent
Classifier: Programming Language :: Python :: 3
Requires-Python: >=3.10
Requires-Dist: faker>=27.0.0
Requires-Dist: httpx>=0.24.1
Requires-Dist: pydantic>=2.6.0
Requires-Dist: pydash>=7.0.6
Requires-Dist: ssort>=0.11.6
Requires-Dist: starlette>=0.27.0
Requires-Dist: toml>=0.10.2
